src/MysosinCK.py
src/__init__.py
src/calculate_and_plot_percent_changes.py
src/overlay_species.py
MyosinCK-0.1.2.dist-info/LICENSE
MyosinCK-0.1.2.dist-info/METADATA
MyosinCK-0.1.2.dist-info/WHEEL
MyosinCK-0.1.2.dist-info/top_level.txt
MyosinCK-0.1.2.dist-info/RECORD
