Metadata-Version: 2.1
Name: MyosinCK
Version: 0.1.2
Summary: The goal of this program is to establish a visualization tool tailored to describing cardiac-specific muscle dynamics and how the alterations of parameters mentioned above (due to disease mutations) can impact the efficiency of muscle dynamics.
Home-page: https://github.com/jeffp12/Myosin-Crossbridge-Cycling-Kinetics
Download-URL: https://github.com/jeffp12/Myosin-Crossbridge-Cycling-Kinetics/archive/refs/tags/jeffp12uw.tar.gz
Author: Jeffrey Pham
Author-email: jeffp12@uw.edu
Classifier: Programming Language :: Python :: 3
Classifier: License :: OSI Approved :: MIT License
Classifier: Operating System :: OS Independent
Requires-Python: >=3.7
License-File: LICENSE
Requires-Dist: numpy>=1.21.0
Requires-Dist: matplotlib>=3.4.0
Requires-Dist: tellurium>=2.0.0
